llmaz/README.md
llmaz/__init__.py
llmaz/main.py
llmaz/model_loader/__init__.py
llmaz/model_loader/constant.py
llmaz/model_loader/model_hub/__init__.py
llmaz/model_loader/model_hub/hub_factory.py
llmaz/model_loader/model_hub/huggingface.py
llmaz/model_loader/model_hub/model_hub.py
llmaz/model_loader/model_hub/modelscope.py
llmaz/model_loader/model_hub/util.py
llmaz/model_loader/objstore/__init__.py
llmaz/model_loader/objstore/objstore.py
llmaz/tests/__init__.py
llmaz/tests/test_hub_factory.py
llmaz/util/__init__.py
llmaz/util/logger.py
llmaz-0.0.1.dist-info/LICENSE
llmaz-0.0.1.dist-info/METADATA
llmaz-0.0.1.dist-info/WHEEL
llmaz-0.0.1.dist-info/RECORD
