Metadata-Version: 2.1
Name: llmaz
Version: 0.0.1
Summary: ☸️ Easy, advanced inference platform for large language models on Kubernetes
License: Apache-2.0
Author: InftyAI Community
Requires-Python: >=3.10,<4.0
Classifier: License :: OSI Approved :: Apache Software License
Classifier: Programming Language :: Python :: 3
Classifier: Programming Language :: Python :: 3.10
Classifier: Programming Language :: Python :: 3.11
Requires-Dist: huggingface-hub (>=0.23.5,<0.24.0)
Requires-Dist: modelscope (>=1.17.0,<2.0.0)
Requires-Dist: omnistore (>=0.0.4,<0.0.5)
